SLiCAP/SLiCAP.py
SLiCAP/SLiCAPconfigure.py
SLiCAP/SLiCAPdesignData.py
SLiCAP/SLiCAPexecute.py
SLiCAP/SLiCAPfc.py
SLiCAP/SLiCAPgschem.py
SLiCAP/SLiCAPhtml.py
SLiCAP/SLiCAPinstruction.py
SLiCAP/SLiCAPkicad.py
SLiCAP/SLiCAPlatex.py
SLiCAP/SLiCAPlex.py
SLiCAP/SLiCAPltspice.py
SLiCAP/SLiCAPmath.py
SLiCAP/SLiCAPmatrices.py
SLiCAP/SLiCAPngspice.py
SLiCAP/SLiCAPplots.py
SLiCAP/SLiCAPprotos.py
SLiCAP/SLiCAPrst.py
SLiCAP/SLiCAPshell.py
SLiCAP/SLiCAPstatespace.py
SLiCAP/SLiCAPsvgTools.py
SLiCAP/SLiCAPyacc.py
SLiCAP/__init__.py
testingslicappip-3.2.8.dist-info/LICENCE.txt
testingslicappip-3.2.8.dist-info/METADATA
testingslicappip-3.2.8.dist-info/WHEEL
testingslicappip-3.2.8.dist-info/top_level.txt
testingslicappip-3.2.8.dist-info/RECORD
