Metadata-Version: 2.2
Name: testingslicappip
Version: 3.2.8
Summary: Symbolic Linear Circuit Analysis Program
Home-page: https://github.com/Tim-van-den-Akker/testingslicappip/
Author: Anton Montagne
Author-email: anton@montagne.nl
Classifier: Programming Language :: Python :: 3
Classifier: Operating System :: OS Independent
Requires-Python: >=3.12
License-File: LICENCE.txt
Requires-Dist: docutils>=0.18
Requires-Dist: numpy>=1.26
Requires-Dist: sympy>=1.12
Requires-Dist: scipy>=1.12
Requires-Dist: ply>=3.11
Requires-Dist: matplotlib>=3.8.0
Requires-Dist: sphinx-rtd-theme>=1.2.0
Requires-Dist: svgelements>=1.9.6
Requires-Dist: cairosvg>=2.7.1
Requires-Dist: IPython>=8.19
Requires-Dist: windows_tools>=2.4; sys_platform == "win32"
Requires-Dist: pywin32>306; sys_platform == "win32"
Dynamic: author
Dynamic: author-email
Dynamic: classifier
Dynamic: description
Dynamic: description-content-type
Dynamic: home-page
Dynamic: requires-dist
Dynamic: requires-python
Dynamic: summary
